core/__init__.py
core/common/__init__.py
core/common/utils/__init__.py
core/common/utils/exceptions.py
core/common/utils/logger.py
core/pipeline/__init__.py
core/pipeline/config.py
core/pipeline/pipeline.py
core/services/extractor/__init__.py
core/services/layout_parser/__init__.py
core/services/observability/__init__.py
core/services/observability/logger/__init__.py
core/services/observability/tracer/__init__.py
core/services/ocr/__init__.py
core/services/post_processor/__init__.py
core/services/schema_generator/__init__.py
leapx-0.1.2.dist-info/METADATA
leapx-0.1.2.dist-info/WHEEL
leapx-0.1.2.dist-info/top_level.txt
leapx-0.1.2.dist-info/RECORD
