Metadata-Version: 2.4
Name: leapx
Version: 0.1.2
Summary: Add your description here
Requires-Python: >=3.12
Requires-Dist: black>=25.11.0
Requires-Dist: pre-commit>=4.4.0
Requires-Dist: pytest>=9.0.0
Requires-Dist: ruff>=0.14.4
